LICENSE
MANIFEST.in
NOTICE
README.md
THANKS
TODO.rst
UNLICENSE
setup.py
docs/Makefile
docs/applications.rst
docs/command-line.rst
docs/conf.py
docs/console_output.rst
docs/events.rst
docs/gaffer.rst
docs/gaffer_lookupd.rst
docs/gafferd.rst
docs/gafferpm_ext.py
docs/getting-started.rst
docs/http.rst
docs/http_handler.rst
docs/httpclient.rst
docs/index.rst
docs/make.bat
docs/manager.rst
docs/news.rst
docs/overview.rst
docs/pidfile.rst
docs/process.rst
docs/processframework.rst
docs/procfile.rst
docs/sig_handler.rst
docs/tornado_pyuv.rst
docs/util.rst
docs/webhooks.rst
docs/_static/gaffer_ps.png
docs/_static/gaffer_watch.png
docs/_static/gafferp.png
examples/echo_client.py
examples/echo_stream.py
examples/job.json
examples/job_custom_stream.json
examples/jobs.json
examples/config/dummy.py
examples/config/echo.py
examples/config/gaffer.ini
examples/config/tmp9yzvmd
examples/config/tmpkb_0xh
examples/config/plugins/dummy/_site/index.html
examples/config/plugins/dummy/dummy/__init__.py
examples/config/plugins/dummy/dummy/app.py
examples/config/plugins/dummy/dummy/main.py
examples/config/plugins/dummy1/_site/index.html
examples/config/plugins/dummy1/dummy1/__init__.py
examples/config/plugins/dummy1/dummy1/main.py
examples/config/plugins/hello/index.html
examples/procfile/Procfile
examples/procfile/dummy.py
examples/procfile/dummy_basic.py
examples/procfile/echo.py
examples/procfile/server.crt
examples/procfile/server.key
examples/procfile/test.env
examples/sockjs/chat/README.md
examples/sockjs/chat/chat.py
examples/sockjs/chat/chat_console.py
examples/sockjs/chat/index.html
gaffer/__init__.py
gaffer/console_output.py
gaffer/controller.py
gaffer/docopt.py
gaffer/error.py
gaffer/events.py
gaffer/manager.py
gaffer/message.py
gaffer/pidfile.py
gaffer/process.py
gaffer/procfile.py
gaffer/pubsub.py
gaffer/sig_handler.py
gaffer/state.py
gaffer/sync.c
gaffer/tornado_pyuv.py
gaffer/util.py
gaffer/webhooks.py
gaffer.egg-info/PKG-INFO
gaffer.egg-info/SOURCES.txt
gaffer.egg-info/dependency_links.txt
gaffer.egg-info/entry_points.txt
gaffer.egg-info/requires.txt
gaffer.egg-info/top_level.txt
gaffer/cli/__init__.py
gaffer/cli/main.py
gaffer/cli/commands/__init__.py
